{"singlePage": ["about"], "startSite": "06/09/2014", "filingNum": "", "onePageListNum": 15, "commentLabelColor": "#006b75", "yearColorList": ["#bc4c00", "#0969da", "#1f883d", "#A333D0"], "i18n": "CN", "themeMode": "manual", "dayTheme": "light", "nightTheme": "dark", "urlMode": "pinyin", "script": "", "style": "", "head": "", "indexScript": "", "indexStyle": "", "bottomText": "", "showPostSource": 1, "iconList": {}, "UTC": 8, "rssSplit": "sentence", "exlink": {}, "needComment": 1, "allHead": "<script src='https://hacker4257.github.io/assets/GmeekVercount.js'></script>", "title": "Love life Love code", "subTitle": "Love life Love code", "avatarUrl": "https://hacker4257.github.io/ava.jpeg", "faviconUrl": "https://hacker4257.github.io/avat.jpg", "GMEEK_VERSION": "last", "homeUrl": "https://hacker4257.github.io/", "postListJson": {"P1": {"htmlDir": "docs/post/hello world.html", "labels": ["\u60f3\u6cd5"], "postTitle": "hello world", "postUrl": "post/hello%20world.html", "postSourceUrl": "https://github.com/hacker4257/hacker4257.github.io/issues/1", "commentNum": 1, "wordCount": 81, "description": "\u5f00\u901a\u535a\u5ba2\u7b2c\u4e00\u7bc7\u5199\u70b9\u4ec0\u4e48\u5462\uff1f \u6ca1\u6709\u4ec0\u4e48\u6bd4 hello world \u7ecf\u5178\u3002", "top": 0, "createdAt": 1402272815, "style": "", "script": "", "head": "", "ogImage": "https://hacker4257.github.io/ava.jpeg", "createdDate": "2014-06-09", "dateLabelColor": "#1f883d"}, "P15": {"htmlDir": "docs/post/cong-ling-xue-Python-xi-lie-di-yi-ke.html", "labels": ["\u8ba1\u7b97\u673a", "\u4ee3\u7801", "\u7f16\u7a0b"], "postTitle": "\u4ece\u96f6\u5b66Python\u7cfb\u5217\u7b2c\u4e00\u8bfe", "postUrl": "post/cong-ling-xue-Python-xi-lie-di-yi-ke.html", "postSourceUrl": "https://github.com/hacker4257/hacker4257.github.io/issues/15", "commentNum": 0, "wordCount": 2226, "description": "### Python\u57fa\u7840\r\n\r\n#### 1. Python\u7b80\u4ecb\r\n\r\nPython\u662f\u4e00\u79cd\u5e7f\u6cdb\u4f7f\u7528\u7684\u9ad8\u7ea7\u7f16\u7a0b\u8bed\u8a00\uff0c\u5b83\u7531Guido van Rossum\u57281989\u5e74\u8bbe\u8ba1\u5e76\u4e8e1991\u5e74\u9996\u6b21\u53d1\u5e03\u3002", "top": 0, "createdAt": 1442980179, "style": "", "script": "", "head": "", "ogImage": "https://hacker4257.github.io/ava.jpeg", "createdDate": "2015-09-23", "dateLabelColor": "#A333D0"}, "P16": {"htmlDir": "docs/post/li-yue-ao-yun-hui.html", "labels": ["\u751f\u6d3b"], "postTitle": "\u91cc\u7ea6\u5965\u8fd0\u4f1a", "postUrl": "post/li-yue-ao-yun-hui.html", "postSourceUrl": "https://github.com/hacker4257/hacker4257.github.io/issues/16", "commentNum": 0, "wordCount": 785, "description": "\u91cc\u7ea6\u70ed\u5185\u5362\u5965\u8fd0\u4f1a\uff082016\u5e74\u590f\u5b63\u5965\u6797\u5339\u514b\u8fd0\u52a8\u4f1a\uff09\u662f\u4e00\u9879\u5168\u7403\u6027\u7684\u4f53\u80b2\u76db\u4e8b\uff0c\u4e8e2016\u5e748\u67085\u65e5\u81f321\u65e5\u5728\u5df4\u897f\u91cc\u7ea6\u70ed\u5185\u5362\u4e3e\u884c\u3002", "top": 0, "createdAt": 1477195250, "style": "", "script": "", "head": "", "ogImage": "https://hacker4257.github.io/ava.jpeg", "createdDate": "2016-10-23", "dateLabelColor": "#bc4c00"}, "P10": {"htmlDir": "docs/post/docker-jian-jie.html", "labels": ["\u8ba1\u7b97\u673a", "\u4ee3\u7801", "\u7f16\u7a0b"], "postTitle": "docker\u7b80\u4ecb", "postUrl": "post/docker-jian-jie.html", "postSourceUrl": "https://github.com/hacker4257/hacker4257.github.io/issues/10", "commentNum": 0, "wordCount": 1170, "description": "### Docker: \u5f15\u9886\u5bb9\u5668\u5316\u6280\u672f\u7684\u9769\u547d\r\n\r\n\u5728\u8f6f\u4ef6\u5f00\u53d1\u548c\u90e8\u7f72\u7684\u4e16\u754c\u4e2d\uff0cDocker \u5df2\u7ecf\u6210\u4e3a\u4e00\u4e2a\u9769\u547d\u6027\u7684\u540d\u8bcd\u3002", "top": 0, "createdAt": 1496980588, "style": "", "script": "", "head": "", "ogImage": "https://hacker4257.github.io/ava.jpeg", "createdDate": "2017-06-09", "dateLabelColor": "#0969da"}, "P12": {"htmlDir": "docs/post/docker-chang-jian-ming-ling.html", "labels": ["\u8ba1\u7b97\u673a", "\u4ee3\u7801", "\u7f16\u7a0b"], "postTitle": "docker\u5e38\u89c1\u547d\u4ee4", "postUrl": "post/docker-chang-jian-ming-ling.html", "postSourceUrl": "https://github.com/hacker4257/hacker4257.github.io/issues/12", "commentNum": 0, "wordCount": 1681, "description": "### 1. \u57fa\u7840\u547d\u4ee4\r\n\r\n- **\u67e5\u770b Docker \u7248\u672c**\r\n  ```bash\r\n  docker --version\r\n  ```\r\n\r\n- **\u67e5\u770b Docker \u72b6\u6001**\r\n  ```bash\r\n  docker info\r\n  ```\r\n\r\n### 2. \u5bb9\u5668\u64cd\u4f5c\r\n\r\n- **\u62c9\u53d6\u955c\u50cf**\r\n  ```bash\r\n  docker pull <image_name>\r\n  ```\r\n  \u4ece Docker Hub \u62c9\u53d6\u6307\u5b9a\u955c\u50cf\u3002", "top": 0, "createdAt": 1498060609, "style": "", "script": "", "head": "", "ogImage": "https://hacker4257.github.io/ava.jpeg", "createdDate": "2017-06-21", "dateLabelColor": "#0969da"}, "P7": {"htmlDir": "docs/post/\u300a-xing-ji-chuan-yue-\u300b\uff1a-ke-xue-yu-qing-gan-de-wan-mei-jiao-zhi.html", "labels": ["\u751f\u6d3b", "\u7535\u5f71"], "postTitle": "\u300a\u661f\u9645\u7a7f\u8d8a\u300b\uff1a\u79d1\u5b66\u4e0e\u60c5\u611f\u7684\u5b8c\u7f8e\u4ea4\u7ec7", "postUrl": "post/%E3%80%8A-xing-ji-chuan-yue-%E3%80%8B%EF%BC%9A-ke-xue-yu-qing-gan-de-wan-mei-jiao-zhi.html", "postSourceUrl": "https://github.com/hacker4257/hacker4257.github.io/issues/7", "commentNum": 0, "wordCount": 2390, "description": "## \u5f15\u8a00\r\n![\u4e0b\u8f7d](https://github.com/user-attachments/assets/d8bd62fb-072c-4e26-9a5a-0ef1e9b5a76e)\r\n\r\n**\u300a\u661f\u9645\u7a7f\u8d8a\u300b**\uff08*Interstellar*\uff09\uff0c\u662f\u7531\u514b\u91cc\u65af\u6258\u5f17\u00b7\u8bfa\u5170\uff08Christopher Nolan\uff09\u6267\u5bfc\u7684\u79d1\u5e7b\u7535\u5f71\uff0c\u4e8e2014\u5e74\u4e0a\u6620\u3002", "top": 0, "createdAt": 1538401362, "style": "", "script": "", "head": "", "ogImage": "https://hacker4257.github.io/ava.jpeg", "createdDate": "2018-10-01", "dateLabelColor": "#1f883d"}, "P18": {"htmlDir": "docs/post/kuai-pai.html", "labels": ["\u8ba1\u7b97\u673a", "\u4ee3\u7801", "\u7f16\u7a0b"], "postTitle": "\u5feb\u6392", "postUrl": "post/kuai-pai.html", "postSourceUrl": "https://github.com/hacker4257/hacker4257.github.io/issues/18", "commentNum": 0, "wordCount": 1244, "description": "\u5feb\u901f\u6392\u5e8f\u662f\u4e00\u79cd\u9ad8\u6548\u7684\u6392\u5e8f\u7b97\u6cd5\uff0c\u4f7f\u7528\u5206\u6cbb\u6cd5\uff08Divide and Conquer\uff09\u7b56\u7565\u6765\u628a\u4e00\u4e2a\u5e8f\u5217\u5206\u4e3a\u8f83\u5c0f\u548c\u8f83\u5927\u7684\u4e24\u4e2a\u5b50\u5e8f\u5217\uff0c\u7136\u540e\u9012\u5f52\u5730\u6392\u5e8f\u4e24\u4e2a\u5b50\u5e8f\u5217\u3002", "top": 0, "createdAt": 1564657387, "style": "", "script": "", "head": "", "ogImage": "https://hacker4257.github.io/ava.jpeg", "createdDate": "2019-08-01", "dateLabelColor": "#A333D0"}, "P20": {"htmlDir": "docs/post/dui-pai-xu.html", "labels": ["\u8ba1\u7b97\u673a", "\u4ee3\u7801", "\u7f16\u7a0b"], "postTitle": "\u5806\u6392\u5e8f", "postUrl": "post/dui-pai-xu.html", "postSourceUrl": "https://github.com/hacker4257/hacker4257.github.io/issues/20", "commentNum": 0, "wordCount": 2247, "description": "\u5806\u6392\u5e8f\u662f\u4e00\u79cd\u9009\u62e9\u6392\u5e8f\u7684\u53d8\u5f62\uff0c\u5b83\u5229\u7528\u5806\u8fd9\u79cd\u6570\u636e\u7ed3\u6784\u7684\u7279\u6027\u6765\u5b9e\u73b0\u6392\u5e8f\u3002", "top": 0, "createdAt": 1569310919, "style": "", "script": "", "head": "", "ogImage": "https://hacker4257.github.io/ava.jpeg", "createdDate": "2019-09-24", "dateLabelColor": "#A333D0"}, "P4": {"htmlDir": "docs/post/tui-jian-shu-ji----\u300a-wo-de-di-yi-ben-suan-fa-shu-\u300b.html", "labels": ["\u751f\u6d3b", "\u597d\u7269", "\u4e66"], "postTitle": "\u63a8\u8350\u4e66\u7c4d---\u300a\u6211\u7684\u7b2c\u4e00\u672c\u7b97\u6cd5\u4e66\u300b", "postUrl": "post/tui-jian-shu-ji----%E3%80%8A-wo-de-di-yi-ben-suan-fa-shu-%E3%80%8B.html", "postSourceUrl": "https://github.com/hacker4257/hacker4257.github.io/issues/4", "commentNum": 0, "wordCount": 1115, "description": "### \u63a8\u8350\u9605\u8bfb\uff1a\u300a\u6211\u7684\u7b2c\u4e00\u672c\u7b97\u6cd5\u4e66\u300b\r\n![image-20240920175559189](https://github.com/user-attachments/assets/5ac15193-ca77-4a59-a049-2e77dc4dc1e9)\r\n\r\n\u5f53\u6211\u4eec\u8c08\u8bba\u7f16\u7a0b\u548c\u6570\u636e\u7ed3\u6784\u65f6\uff0c\u7b97\u6cd5\u662f\u4e00\u4e2a\u4e0d\u53ef\u6216\u7f3a\u7684\u4e3b\u9898\u3002", "top": 0, "createdAt": 1601546391, "style": "", "script": "", "head": "", "ogImage": "https://hacker4257.github.io/ava.jpeg", "createdDate": "2020-10-01", "dateLabelColor": "#bc4c00"}, "P8": {"htmlDir": "docs/post/ 2021-nian-ge-ren-nian-du-zong-jie.html", "labels": ["\u751f\u6d3b", "\u60f3\u6cd5"], "postTitle": " 2021\u5e74\u4e2a\u4eba\u5e74\u5ea6\u603b\u7ed3", "postUrl": "post/%202021-nian-ge-ren-nian-du-zong-jie.html", "postSourceUrl": "https://github.com/hacker4257/hacker4257.github.io/issues/8", "commentNum": 0, "wordCount": 817, "description": "2021\u5e74\u5bf9\u6211\u6765\u8bf4\u662f\u5145\u6ee1\u6311\u6218\u4e0e\u6210\u957f\u7684\u4e00\u5e74\u3002", "top": 0, "createdAt": 1640966340, "style": "", "script": "", "head": "", "ogImage": "https://hacker4257.github.io/ava.jpeg", "createdDate": "2021-12-31", "dateLabelColor": "#0969da"}, "P6": {"htmlDir": "docs/post/er-fen-cha-zhao-\uff1a-gao-xiao-jie-jue-pai-xu-wen-ti-de-suan-fa.html", "labels": ["\u8ba1\u7b97\u673a", "\u4ee3\u7801", "\u7f16\u7a0b"], "postTitle": "\u4e8c\u5206\u67e5\u627e\uff1a\u9ad8\u6548\u89e3\u51b3\u6392\u5e8f\u95ee\u9898\u7684\u7b97\u6cd5", "postUrl": "post/er-fen-cha-zhao-%EF%BC%9A-gao-xiao-jie-jue-pai-xu-wen-ti-de-suan-fa.html", "postSourceUrl": "https://github.com/hacker4257/hacker4257.github.io/issues/6", "commentNum": 0, "wordCount": 2842, "description": "## \u5f15\u8a00\r\n\r\n\u5728\u8ba1\u7b97\u673a\u79d1\u5b66\u4e2d\uff0c\u67e5\u627e\u95ee\u9898\u662f\u975e\u5e38\u5e38\u89c1\u7684\u4efb\u52a1\u4e4b\u4e00\uff0c\u5c24\u5176\u662f\u5728\u5904\u7406\u5927\u91cf\u6570\u636e\u65f6\u3002", "top": 0, "createdAt": 1660095762, "style": "", "script": "", "head": "", "ogImage": "https://hacker4257.github.io/ava.jpeg", "createdDate": "2022-08-10", "dateLabelColor": "#1f883d"}, "P17": {"htmlDir": "docs/post/cong-ling-xue-Go-xi-lie-di-yi-ke.html", "labels": ["\u8ba1\u7b97\u673a", "\u4ee3\u7801", "\u7f16\u7a0b"], "postTitle": "\u4ece\u96f6\u5b66Go\u7cfb\u5217\u7b2c\u4e00\u8bfe", "postUrl": "post/cong-ling-xue-Go-xi-lie-di-yi-ke.html", "postSourceUrl": "https://github.com/hacker4257/hacker4257.github.io/issues/17", "commentNum": 0, "wordCount": 801, "description": "## \u57fa\u7840\u7bc7\r\n### \u7b2c\u4e00\u6b65\uff1a\u5b89\u88c5Go\r\n\r\n1. \u8bbf\u95eeGo\u8bed\u8a00\u7684\u5b98\u65b9\u7f51\u7ad9\uff1ahttps://golang.org/\r\n2. \u70b9\u51fb\u4e0b\u8f7d\u9875\u9762\uff0c\u9009\u62e9\u9002\u5408\u4f60\u7684\u64cd\u4f5c\u7cfb\u7edf\u7684\u5b89\u88c5\u5305\uff08Windows\u3001macOS\u6216Linux\uff09\u3002", "top": 0, "createdAt": 1672552987, "style": "", "script": "", "head": "", "ogImage": "https://hacker4257.github.io/ava.jpeg", "createdDate": "2023-01-01", "dateLabelColor": "#A333D0"}, "P11": {"htmlDir": "docs/post/she-ji-mo-shi-zhi-mo-ban-mo-shi.html", "labels": ["\u8ba1\u7b97\u673a", "\u4ee3\u7801", "\u7f16\u7a0b"], "postTitle": "\u8bbe\u8ba1\u6a21\u5f0f\u4e4b\u6a21\u677f\u6a21\u5f0f", "postUrl": "post/she-ji-mo-shi-zhi-mo-ban-mo-shi.html", "postSourceUrl": "https://github.com/hacker4257/hacker4257.github.io/issues/11", "commentNum": 0, "wordCount": 2000, "description": "\u6a21\u677f\u65b9\u6cd5\u6a21\u5f0f\u662f\u4e00\u79cd\u884c\u4e3a\u8bbe\u8ba1\u6a21\u5f0f\uff0c\u5b83\u5b9a\u4e49\u4e86\u4e00\u4e2a\u7b97\u6cd5\u7684\u9aa8\u67b6\uff0c\u5141\u8bb8\u5b50\u7c7b\u5728\u4e0d\u6539\u53d8\u7b97\u6cd5\u7ed3\u6784\u7684\u60c5\u51b5\u4e0b\u91cd\u5b9a\u4e49\u7b97\u6cd5\u7684\u67d0\u4e9b\u7279\u5b9a\u6b65\u9aa4\u3002", "top": 0, "createdAt": 1726635786, "style": "", "script": "", "head": "", "ogImage": "https://hacker4257.github.io/ava.jpeg", "createdDate": "2024-09-18", "dateLabelColor": "#bc4c00"}, "P3": {"htmlDir": "docs/post/she-ji-mo-shi-zhi-ming-ling-mo-shi.html", "labels": ["\u8ba1\u7b97\u673a", "\u4ee3\u7801", "\u7f16\u7a0b"], "postTitle": "\u8bbe\u8ba1\u6a21\u5f0f\u4e4b\u547d\u4ee4\u6a21\u5f0f", "postUrl": "post/she-ji-mo-shi-zhi-ming-ling-mo-shi.html", "postSourceUrl": "https://github.com/hacker4257/hacker4257.github.io/issues/3", "commentNum": 0, "wordCount": 3635, "description": "## \u547d\u4ee4\u6a21\u5f0f\r\n\u547d\u4ee4\u6a21\u5f0f\uff08Command Pattern\uff09\u662f\u4e00\u79cd\u884c\u4e3a\u578b\u8bbe\u8ba1\u6a21\u5f0f\uff0c\u5b83\u4e3b\u8981\u76ee\u7684\u662f\u5c06\u8bf7\u6c42\u6216\u7b80\u5355\u64cd\u4f5c\u5c01\u88c5\u4e3a\u4e00\u4e2a\u5bf9\u8c61\u3002", "top": 0, "createdAt": 1726705822, "style": "", "script": "", "head": "", "ogImage": "https://hacker4257.github.io/ava.jpeg", "createdDate": "2024-09-19", "dateLabelColor": "#bc4c00"}, "P2": {"htmlDir": "docs/post/she-ji-mo-shi-zhi-guan-cha-zhe-mo-shi.html", "labels": ["\u8ba1\u7b97\u673a", "\u4ee3\u7801", "\u7f16\u7a0b"], "postTitle": "\u8bbe\u8ba1\u6a21\u5f0f\u4e4b\u89c2\u5bdf\u8005\u6a21\u5f0f", "postUrl": "post/she-ji-mo-shi-zhi-guan-cha-zhe-mo-shi.html", "postSourceUrl": "https://github.com/hacker4257/hacker4257.github.io/issues/2", "commentNum": 0, "wordCount": 4865, "description": "## \u89c2\u5bdf\u8005\u6a21\u5f0f\r\n\u89c2\u5bdf\u8005\u6a21\u5f0f\uff08Observer Pattern\uff09\u662f\u4e00\u79cd\u5e38\u7528\u7684\u8f6f\u4ef6\u8bbe\u8ba1\u6a21\u5f0f\uff0c\u5c5e\u4e8e\u884c\u4e3a\u578b\u6a21\u5f0f\u3002", "top": 0, "createdAt": 1726814953, "style": "", "script": "", "head": "", "ogImage": "https://hacker4257.github.io/ava.jpeg", "createdDate": "2024-09-20", "dateLabelColor": "#bc4c00"}, "P9": {"htmlDir": "docs/post/she-ji-mo-shi-zhi-fang-wen-mo-shi.html", "labels": ["\u8ba1\u7b97\u673a", "\u4ee3\u7801", "\u7f16\u7a0b"], "postTitle": "\u8bbe\u8ba1\u6a21\u5f0f\u4e4b\u8bbf\u95ee\u6a21\u5f0f", "postUrl": "post/she-ji-mo-shi-zhi-fang-wen-mo-shi.html", "postSourceUrl": "https://github.com/hacker4257/hacker4257.github.io/issues/9", "commentNum": 0, "wordCount": 3240, "description": "\r\n\u8bbf\u95ee\u6a21\u5f0f\uff08Visitor Pattern\uff09\u662f\u4e00\u79cd\u884c\u4e3a\u578b\u8bbe\u8ba1\u6a21\u5f0f\uff0c\u5b83\u5141\u8bb8\u5728\u4e0d\u4fee\u6539\u5df2\u6709\u7a0b\u5e8f\u7ed3\u6784\u7684\u60c5\u51b5\u4e0b\uff0c\u5411\u5df2\u6709\u7684\u5bf9\u8c61\u7ed3\u6784\u4e2d\u6dfb\u52a0\u65b0\u7684\u64cd\u4f5c\u3002", "top": 0, "createdAt": 1726889561, "style": "", "script": "", "head": "", "ogImage": "https://hacker4257.github.io/ava.jpeg", "createdDate": "2024-09-21", "dateLabelColor": "#bc4c00"}, "P13": {"htmlDir": "docs/post/she-ji-mo-shi-zhi-ce-lve-mo-shi.html", "labels": ["\u8ba1\u7b97\u673a", "\u4ee3\u7801", "\u7f16\u7a0b"], "postTitle": "\u8bbe\u8ba1\u6a21\u5f0f\u4e4b\u7b56\u7565\u6a21\u5f0f", "postUrl": "post/she-ji-mo-shi-zhi-ce-lve-mo-shi.html", "postSourceUrl": "https://github.com/hacker4257/hacker4257.github.io/issues/13", "commentNum": 0, "wordCount": 3040, "description": "\u7b56\u7565\u6a21\u5f0f\uff08Strategy Pattern\uff09\u662f\u4e00\u79cd\u5e38\u7528\u7684\u8bbe\u8ba1\u6a21\u5f0f\uff0c\u5c5e\u4e8e\u884c\u4e3a\u578b\u6a21\u5f0f\u3002", "top": 0, "createdAt": 1726980441, "style": "", "script": "", "head": "", "ogImage": "https://hacker4257.github.io/ava.jpeg", "createdDate": "2024-09-22", "dateLabelColor": "#bc4c00"}, "P14": {"htmlDir": "docs/post/she-ji-mo-shi-zhi-shi-pei-qi-mo-shi.html", "labels": ["\u8ba1\u7b97\u673a", "\u4ee3\u7801", "\u7f16\u7a0b"], "postTitle": "\u8bbe\u8ba1\u6a21\u5f0f\u4e4b\u9002\u914d\u5668\u6a21\u5f0f", "postUrl": "post/she-ji-mo-shi-zhi-shi-pei-qi-mo-shi.html", "postSourceUrl": "https://github.com/hacker4257/hacker4257.github.io/issues/14", "commentNum": 0, "wordCount": 2212, "description": "## \u9002\u914d\u5668\u6a21\u5f0f\r\n\r\n\u9002\u914d\u5668\u6a21\u5f0f\uff08Adapter Pattern\uff09\u662f\u4e00\u79cd\u7ed3\u6784\u578b\u8bbe\u8ba1\u6a21\u5f0f\uff0c\u5b83\u5141\u8bb8\u4e0d\u517c\u5bb9\u7684\u63a5\u53e3\u4e4b\u95f4\u8fdb\u884c\u4ea4\u4e92\u3002", "top": 0, "createdAt": 1727060288, "style": "", "script": "", "head": "", "ogImage": "https://hacker4257.github.io/ava.jpeg", "createdDate": "2024-09-23", "dateLabelColor": "#bc4c00"}, "P19": {"htmlDir": "docs/post/she-ji-mo-shi-zhi-zu-he-mo-shi.html", "labels": ["\u8ba1\u7b97\u673a", "\u4ee3\u7801", "\u7f16\u7a0b"], "postTitle": "\u8bbe\u8ba1\u6a21\u5f0f\u4e4b\u7ec4\u5408\u6a21\u5f0f", "postUrl": "post/she-ji-mo-shi-zhi-zu-he-mo-shi.html", "postSourceUrl": "https://github.com/hacker4257/hacker4257.github.io/issues/19", "commentNum": 0, "wordCount": 2898, "description": "## \u7ec4\u5408\u6a21\u5f0f\r\n\u7ec4\u5408\u6a21\u5f0f\u662f\u4e00\u79cd\u7ed3\u6784\u578b\u8bbe\u8ba1\u6a21\u5f0f\uff0c\u7528\u4e8e\u5c06\u5bf9\u8c61\u7ec4\u7ec7\u6210\u6811\u5f62\u7ed3\u6784\u4ee5\u8868\u793a\u90e8\u5206-\u6574\u4f53\u7684\u5c42\u6b21\u5173\u7cfb\u3002", "top": 0, "createdAt": 1727145429, "style": "", "script": "", "head": "", "ogImage": "https://hacker4257.github.io/ava.jpeg", "createdDate": "2024-09-24", "dateLabelColor": "#bc4c00"}, "P21": {"htmlDir": "docs/post/she-ji-mo-shi-zhi-han-shu-xuan-xiang-mo-shi.html", "labels": ["\u8ba1\u7b97\u673a", "\u4ee3\u7801", "\u7f16\u7a0b"], "postTitle": "\u8bbe\u8ba1\u6a21\u5f0f\u4e4b\u51fd\u6570\u9009\u9879\u6a21\u5f0f", "postUrl": "post/she-ji-mo-shi-zhi-han-shu-xuan-xiang-mo-shi.html", "postSourceUrl": "https://github.com/hacker4257/hacker4257.github.io/issues/21", "commentNum": 0, "wordCount": 2221, "description": "## \u51fd\u6570\u9009\u9879\u6a21\u5f0f\r\n\r\n\u51fd\u6570\u9009\u9879\u6a21\u5f0f\uff08Functional Options Pattern\uff09\u5728Go\u8bed\u8a00\u4e2d\u662f\u4e00\u79cd\u6d41\u884c\u7684\u8bbe\u8ba1\u6a21\u5f0f\uff0c\u7528\u4e8e\u6784\u5efa\u7075\u6d3b\u4e14\u6613\u4e8e\u6269\u5c55\u7684API\u3002", "top": 0, "createdAt": 1727233161, "style": "", "script": "", "head": "", "ogImage": "https://hacker4257.github.io/ava.jpeg", "createdDate": "2024-09-25", "dateLabelColor": "#bc4c00"}, "P22": {"htmlDir": "docs/post/cong-ling-xue-shu-ju-jie-gou.html", "labels": ["\u8ba1\u7b97\u673a", "\u4ee3\u7801", "\u7f16\u7a0b"], "postTitle": "\u4ece\u96f6\u5b66\u6570\u636e\u7ed3\u6784", "postUrl": "post/cong-ling-xue-shu-ju-jie-gou.html", "postSourceUrl": "https://github.com/hacker4257/hacker4257.github.io/issues/22", "commentNum": 0, "wordCount": 941, "description": "# \u7b2c\u4e00\u8bfe\uff1a\u6570\u636e\u7ed3\u6784\u6982\u8ff0\u548c\u6570\u7ec4\r\n\r\n\u5728\u8fd9\u4e00\u8bfe\u4e2d\uff0c\u6211\u4eec\u5c06\u9996\u5148\u4e86\u89e3\u6570\u636e\u7ed3\u6784\u7684\u57fa\u672c\u6982\u5ff5\uff0c\u7136\u540e\u6df1\u5165\u5b66\u4e60\u6570\u7ec4\u8fd9\u4e00\u57fa\u672c\u6570\u636e\u7ed3\u6784\u3002", "top": 0, "createdAt": 1727343804, "style": "", "script": "", "head": "", "ogImage": "https://hacker4257.github.io/ava.jpeg", "createdDate": "2024-09-26", "dateLabelColor": "#bc4c00"}, "P23": {"htmlDir": "docs/post/she-ji-mo-shi-zhi-die-dai-qi-mo-shi.html", "labels": ["\u8ba1\u7b97\u673a", "\u4ee3\u7801", "\u7f16\u7a0b"], "postTitle": "\u8bbe\u8ba1\u6a21\u5f0f\u4e4b\u8fed\u4ee3\u5668\u6a21\u5f0f", "postUrl": "post/she-ji-mo-shi-zhi-die-dai-qi-mo-shi.html", "postSourceUrl": "https://github.com/hacker4257/hacker4257.github.io/issues/23", "commentNum": 0, "wordCount": 2570, "description": "## \u8fed\u4ee3\u5668\u6a21\u5f0f\r\n\r\n\u8fed\u4ee3\u5668\u6a21\u5f0f\uff08Iterator Pattern\uff09\u662f\u4e00\u79cd\u884c\u4e3a\u8bbe\u8ba1\u6a21\u5f0f\uff0c\u5b83\u63d0\u4f9b\u4e86\u4e00\u79cd\u987a\u5e8f\u8bbf\u95ee\u96c6\u5408\u5bf9\u8c61\u4e2d\u5404\u4e2a\u5143\u7d20\u7684\u65b9\u6cd5\uff0c\u800c\u4e0d\u9700\u8981\u66b4\u9732\u8be5\u5bf9\u8c61\u7684\u5185\u90e8\u8868\u793a\u3002", "top": 0, "createdAt": 1727406245, "style": "", "script": "", "head": "", "ogImage": "https://hacker4257.github.io/ava.jpeg", "createdDate": "2024-09-27", "dateLabelColor": "#bc4c00"}, "P24": {"htmlDir": "docs/post/she-ji-mo-shi-zhi-mo-ban-fang-fa-mo-shi.html", "labels": ["\u8ba1\u7b97\u673a", "\u4ee3\u7801", "\u7f16\u7a0b"], "postTitle": "\u8bbe\u8ba1\u6a21\u5f0f\u4e4b\u6a21\u677f\u65b9\u6cd5\u6a21\u5f0f", "postUrl": "post/she-ji-mo-shi-zhi-mo-ban-fang-fa-mo-shi.html", "postSourceUrl": "https://github.com/hacker4257/hacker4257.github.io/issues/24", "commentNum": 0, "wordCount": 2489, "description": "## \u6a21\u677f\u65b9\u6cd5\u6a21\u5f0f\r\n\r\n\u6a21\u677f\u65b9\u6cd5\u6a21\u5f0f\u662f\u4e00\u79cd\u884c\u4e3a\u578b\u8bbe\u8ba1\u6a21\u5f0f\uff0c\u5b83\u5b9a\u4e49\u4e86\u4e00\u4e2a\u64cd\u4f5c\u4e2d\u7684\u7b97\u6cd5\u7684\u6846\u67b6\uff0c\u5e76\u5c06\u4e00\u4e9b\u6b65\u9aa4\u7684\u6267\u884c\u5ef6\u8fdf\u5230\u5b50\u7c7b\u4e2d\u3002", "top": 0, "createdAt": 1727505975, "style": "", "script": "", "head": "", "ogImage": "https://hacker4257.github.io/ava.jpeg", "createdDate": "2024-09-28", "dateLabelColor": "#bc4c00"}, "P25": {"htmlDir": "docs/post/she-ji-mo-shi-zhi-bei-wang-lu-mo-shi.html", "labels": ["\u8ba1\u7b97\u673a", "\u4ee3\u7801", "\u7f16\u7a0b"], "postTitle": "\u8bbe\u8ba1\u6a21\u5f0f\u4e4b\u5907\u5fd8\u5f55\u6a21\u5f0f", "postUrl": "post/she-ji-mo-shi-zhi-bei-wang-lu-mo-shi.html", "postSourceUrl": "https://github.com/hacker4257/hacker4257.github.io/issues/25", "commentNum": 0, "wordCount": 2842, "description": "## \u5907\u5fd8\u5f55\u6a21\u5f0f\r\n\u5907\u5fd8\u5f55\u6a21\u5f0f\u662f\u4e00\u79cd\u884c\u4e3a\u8bbe\u8ba1\u6a21\u5f0f\uff0c\u5b83\u5141\u8bb8\u4fdd\u5b58\u548c\u6062\u590d\u5bf9\u8c61\u7684\u5185\u90e8\u72b6\u6001\uff0c\u800c\u65e0\u9700\u66b4\u9732\u8be5\u5bf9\u8c61\u7684\u5b9e\u73b0\u7ec6\u8282\u3002", "top": 0, "createdAt": 1727615352, "style": "", "script": "", "head": "", "ogImage": "https://hacker4257.github.io/ava.jpeg", "createdDate": "2024-09-29", "dateLabelColor": "#bc4c00"}, "P26": {"htmlDir": "docs/post/ru-he-shi-yong-Kubeadm-she-zhi-Kubernetes-ji-qun.html", "labels": ["\u8ba1\u7b97\u673a", "\u4ee3\u7801", "\u7f16\u7a0b"], "postTitle": "\u5982\u4f55\u4f7f\u7528Kubeadm\u8bbe\u7f6eKubernetes\u96c6\u7fa4", "postUrl": "post/ru-he-shi-yong-Kubeadm-she-zhi-Kubernetes-ji-qun.html", "postSourceUrl": "https://github.com/hacker4257/hacker4257.github.io/issues/26", "commentNum": 0, "wordCount": 9594, "description": "### \u5b9e\u9a8c\u73af\u5883\r\nMacBook Pro 16-inch, 2019\r\n\r\n\u5904\u7406\u5668: 2.4 GHz 8-Core Intel Core i9\r\n\r\n\u5185\u5b58: 32 GB 2667 MHz DDR4\r\n\r\nmacos:  Sonoma version 14.2.1 (23C71)\r\n\r\n\u4f7f\u7528UTM\u865a\u62df\u673a\u5de5\u5177\u521b\u5efa3\u53f0ubuntu20.04-arm64\uff0c\u865a\u62df\u673a\u914d\u7f6e\u5747\u4e3a2\u68384G, \u91c7\u75281\u4e2amaster\uff0c 2\u4e2anode\u7684\u6784\u67b6\r\n\r\n###  \u90e8\u7f72\u67b6\u6784\u89c4\u5212\r\n| \u89d2\u8272 | \u4e3b\u673a\u540d | \u7ec4\u4ef6 | IP |\r\n|-------|-------|-------|-------|\r\n| master | master | etcd\u3001apiserver\u3001controller-manager\u3001scheduler\u3001kubelet\u3001proxy\u3001calico\u3001runc |192.168.64.18\r\n|node01|node01|pod\u3001kubelet\u3001proxy\u3001calico\u3001runc|192.168.64.19\r\n|node01|node01|pod\u3001kubelet\u3001proxy\u3001calico\u3001runc|192.168.64.20\r\n\r\n### \u8f6f\u4ef6\u7248\u672c\r\n*docker server \uff1a24.0.7\r\n\r\n*containerd \uff1a1.7.12\r\n\r\n*kubeadm : v1.30.0\r\n\r\n*kubelet : v1.30.0\r\n\r\n*kubectl : v1.30.0\r\n\r\n### \u96c6\u7fa4\u670d\u52a1\u521d\u59cb\u5316 \uff083*\uff0c \u6240\u6709\u673a\u5668\u90fd\u6267\u884c\uff09\r\n#### \u5207\u6362\u4e3a\u7ba1\u7406\u5458\r\n```shell\r\nsudo su\r\n```\r\n#### \u6dfb\u52a0\u4e3b\u673a\u540d\r\n```shell\r\ncat >> /etc/hosts <<EOF\r\n192.168.64.18 master\r\n192.168.64.19 node01\r\n192.168.64.20 node02\r\nEOF\r\n\r\n```\r\n#### \u65f6\u95f4\u540c\u6b65\r\n```shell\r\napt update && apt install ntpdate\r\nntpdate cn.ntp.org.cn\r\n```\r\n#### \u5173\u95ed\u9632\u706b\u5899\r\n```shell\r\nsystemctl disable ufw && systemctl stop ufw\r\n```\r\n#### \u5173\u95edswap\u5206\u533a\r\n```shell\r\nswapoff -a  # \u4e34\u65f6\u5173\u95ed\r\nsed -ri 's/.swap*./#&/g' /etc/fstab   # \u4fee\u6539\u914d\u7f6e\u6587\u4ef6 sed\u4fee\u6539\u914d\u7f6e\u6587\u4ef6\u6c38\u4e45\u5173\u95ed\r\n```\r\n#### \u542f\u7528iptables\u6865\u63a5\u6d41\u91cf\r\n```shell\r\n# \u6dfb\u52a0\u914d\u7f6e\u6587\u4ef6\r\ncat <<EOF | sudo tee /etc/modules-load.d/k8s.conf\r\noverlay\r\nbr_netfilter\r\nEOF\r\n\r\n# \u52a0\u8f7d\u6a21\u5757\r\nmodprobe overlay\r\nmodprobe br_netfilter\r\n\r\n# \u8bbe\u7f6e\u6240\u9700\u7684Sysctl\u53c2\u6570\uff0c\u53c2\u6570\u5728\u91cd\u65b0\u542f\u52a8\u65f6\u4fdd\u6301\u4e0d\u53d8\r\ncat  <<EOF | tee /etc/sysctl.d/k8s.conf\r\nnet.bridge.bridge-nf-call-iptables = 1\r\nnet.bridge.bridge-nf-call-ip6tables = 1\r\nnet.ipv4.ip_forward = 1\r\nvm.swappiness = 0\r\nEOF\r\n\r\n# \u4e0d\u91cd\u542f\u5c31\u5e94\u7528sysctl\u53c2\u6570\r\nsysctl --system\r\n\r\n# \u4fdd\u5b88\u5efa\u8bae\r\nreboot\r\n```\r\n#### \u5b89\u88c5\u5bb9\u5668\u8fd0\u884c\u65f6\r\nk8s\u652f\u6301\u7684\u5bb9\u5668\u8fd0\u884c\u65f6\u6709\u5f88\u591a\u5982docker\u3001containerd\u3001cri-o\u7b49\u7b49\uff0cdocker \u7701\u4e8b\u4e00\u4e9b\uff0c\u8fd9\u91cc\u9009\u62e9\u5b89\u88c5docker\r\n```shell\r\n# \u5b89\u88c5docker\r\napt-get update\r\napt install -y docker.io\r\n\r\n# \u8bbe\u7f6edocker\u5f00\u673a\u81ea\u542f\r\nsystemctl start docker\r\nststemctl enable docker\r\n\r\n# \u4e09\u4e2a\u670d\u52a1\u90fd\u5e94\u662frunning\u72b6\u6001\r\nsystemctl status containerd.service\r\nsystemctl status docker.service\r\nsystemctl status docker.socket\r\n```\r\n\r\n#### \u914d\u7f6e\u5bb9\u5668\u8fd0\u884c\u65f6\u7684systemd\u9a71\u52a8\r\n```shell\r\n\r\nvim /etc/docker/daemon.json \r\n\r\n```\r\n\u7136\u540e\u5c06\u4e0b\u9762\u8bbe\u7f6e\u52a0\u5165daemon.js\r\n```shell\r\n{\r\n  'exec-opts': [\r\n    'native.cgroupdriver=systemd'\r\n  ]\r\n}\r\n\r\n```\r\n\u91cd\u542fdocker\r\n```shell \r\nsystemctl restart docker\r\n```\r\n#### \u8bbe\u7f6eKubernetes APT\u5b58\u50a8\u5e93\u7684GPG\u5bc6\u94a5\r\n```shell \r\nKUBERNETES_VERSION=1.30\r\n\r\nsudo mkdir -p /etc/apt/keyrings\r\n\r\ncurl -fsSL https://pkgs.k8s.io/core:/stable:/v$KUBERNETES_VERSION/deb/Release.key | sudo gpg --dearmor -o /etc/apt/keyrings/kubernetes-apt-keyring.gpg\r\n\r\necho 'deb [signed-by=/etc/apt/keyrings/kubernetes-apt-keyring.gpg] https://pkgs.k8s.io/core:/stable:/v$KUBERNETES_VERSION/deb/ /' | sudo tee /etc/apt/sources.list.d/kubernetes.list\r\n\r\n\r\n```\r\n \u66f4\u65b0 apt \u4ed3\u5e93\r\n ```shell\r\n apt-get update -y\r\n ```\r\n #### \u5b89\u88c5Kubernetes\u7ec4\u4ef6\r\n ```shell \r\n \r\n # \u5b89\u88c5\u4e00\u4e9b\u8f85\u52a9\u5305\r\napt-get install -y apt-transport-https ca-certificates curl gpg\r\n \r\n# \u5b89\u88c5\u6307\u5b9a\u7248\u672c\r\napt-get install -y kubelet=1.30.0-1.1 kubectl=1.30.0-1.1 kubeadm=1.30.0-1.1\r\n\r\n# \u786e\u8ba4\u670d\u52a1\u72b6\u6001\uff08\u6b64\u65f6kubelet\u6682\u672a\u542f\u52a8\uff09\r\nsystemctl status kubelet\r\n ```\r\n ### Kubernetes \u521d\u59cb\u5316\uff08\u53ea\u5728master\u64cd\u4f5c\uff09\r\n ```shell\r\nkubeadm init \\\r\n  --control-plane-endpoint='192.168.64.18' \\\r\n  --service-cidr=10.96.0.0/12 \\\r\n  --pod-network-cidr=10.244.0.0/16 \\\r\n  --ignore-preflight-errors=all\r\n  \r\n# \u2013-apiserver-advertise-address # \u96c6\u7fa4\u901a\u544a\u5730\u5740\uff0c\u5355master\u65f6\u4e3a\u63a7\u5236\u9762\u4f7f\u7528\u7684\u7684\u670d\u52a1\u5668IP\r\n# \u2013-service-cidr #\u96c6\u7fa4\u5185\u90e8\u865a\u62df\u7f51\u7edc\uff0cPod\u7edf\u4e00\u8bbf\u95ee\u5165\u53e3\uff0c\u53ef\u4ee5\u4e0d\u7528\u66f4\u6539\uff0c\u76f4\u63a5\u7528\u4e0a\u9762\u7684\u53c2\u6570\r\n# \u2013-pod-network-cidr #Pod\u7f51\u7edc\uff0c\u4e0e\u4e0b\u9762\u90e8\u7f72\u7684CNI\u7f51\u7edc\u7ec4\u4ef6yaml\u4e2d\u4fdd\u6301\u4e00\u81f4\uff0c\u53ef\u4ee5\u4e0d\u7528\u66f4\u6539\uff0c\u76f4\u63a5\u7528\u4e0a\u9762\u7684\u53c2\u6570\r\n\r\n ```\r\n \u521d\u59cb\u5316\u6210\u529f\u663e\u793a\u5982\u4e0b\r\n ```shell\r\n Your Kubernetes control-plane has initialized successfully!\r\n\r\nTo start using your cluster, you need to run the following as a regular user:\r\n\r\n  mkdir -p $HOME/.kube\r\n  sudo cp -i /etc/kubernetes/admin.conf $HOME/.kube/config\r\n  sudo chown $(id -u):$(id -g) $HOME/.kube/config\r\n\r\nAlternatively, if you are the root user, you can run:\r\n\r\n  export KUBECONFIG=/etc/kubernetes/admin.conf\r\n\r\nYou should now deploy a pod network to the cluster.\r\nRun 'kubectl apply -f [podnetwork].yaml' with one of the options listed at:\r\n  https://kubernetes.io/docs/concepts/cluster-administration/addons/\r\n\r\nYou can now join any number of the control-plane node running the following command on each as root:\r\n\r\n  kubeadm join 192.168.64.18:6443 --token m5pstt.v2gebrasw9yfzxb6 \\\r\n\t--discovery-token-ca-cert-hash sha256:205a991b66a2ec879bd36f66851725fd84201d7306bb088ceda8835ad99450b8 \\\r\n\t--control-plane --certificate-key 34a274a91255cf25cda3af0f6ecbfc2876e97196491338aab72ca1b3bd09e1d1\r\n\r\nPlease note that the certificate-key gives access to cluster sensitive data, keep it secret!\r\nAs a safeguard, uploaded-certs will be deleted in two hours; If necessary, you can use\r\n'kubeadm init phase upload-certs --upload-certs' to reload certs afterward.\r\n\r\nThen you can join any number of worker nodes by running the following on each as root:\r\n\r\nkubeadm join 192.168.64.18:6443 --token m5pstt.v2gebrasw9yfzxb6 \\\r\n\t--discovery-token-ca-cert-hash sha256:205a991b66a2ec879bd36f66851725fd84201d7306bb088ceda8835ad99450b8 \r\n ```\r\n \u4ece\u8f93\u51fa\u4e2d\u4f7f\u7528\u4ee5\u4e0b\u547d\u4ee4\u5728master\u4e2d\u521b\u5efakubeconfig\uff0c\u4ee5\u4fbf\u60a8\u53ef\u4ee5\u4f7f\u7528kubectl\u4e0e\u96c6\u7fa4API\u4ea4\u4e92\u3002", "top": 0, "createdAt": 1727672515, "style": "", "script": "", "head": "", "ogImage": "https://hacker4257.github.io/ava.jpeg", "createdDate": "2024-09-30", "dateLabelColor": "#bc4c00"}, "P27": {"htmlDir": "docs/post/guo-qing-kuai-le.html", "labels": ["\u751f\u6d3b"], "postTitle": "\u56fd\u5e86\u5feb\u4e50", "postUrl": "post/guo-qing-kuai-le.html", "postSourceUrl": "https://github.com/hacker4257/hacker4257.github.io/issues/27", "commentNum": 0, "wordCount": 51, "description": "# enjoy life\r\n<!-- ##{'timestamp':1727748060}## -->\u3002", "top": 0, "createdAt": 1727748060, "style": "", "script": "", "head": "", "ogImage": "https://hacker4257.github.io/ava.jpeg", "createdDate": "2024-10-01", "dateLabelColor": "#bc4c00"}, "P28": {"htmlDir": "docs/post/Leetcode-xi-lie-zhi-Z-zi-xing-bian-huan.html", "labels": ["\u8ba1\u7b97\u673a", "\u4ee3\u7801", "\u7f16\u7a0b"], "postTitle": "Leetcode\u7cfb\u5217\u4e4bZ\u5b57\u884c\u53d8\u6362", "postUrl": "post/Leetcode-xi-lie-zhi-Z-zi-xing-bian-huan.html", "postSourceUrl": "https://github.com/hacker4257/hacker4257.github.io/issues/28", "commentNum": 0, "wordCount": 2779, "description": "### 6. Z \u5b57\u5f62\u53d8\u6362\r\n### \u9898\u76ee\u63cf\u8ff0\r\n\u5c06\u4e00\u4e2a\u7ed9\u5b9a\u5b57\u7b26\u4e32 s \u6839\u636e\u7ed9\u5b9a\u7684\u884c\u6570 numRows \uff0c\u4ee5\u4ece\u4e0a\u5f80\u4e0b\u3001\u4ece\u5de6\u5230\u53f3\u8fdb\u884c Z \u5b57\u5f62\u6392\u5217\u3002", "top": 0, "createdAt": 1727858915, "style": "", "script": "", "head": "", "ogImage": "https://hacker4257.github.io/ava.jpeg", "createdDate": "2024-10-02", "dateLabelColor": "#bc4c00"}, "P29": {"htmlDir": "docs/post/ -ti-shi-gong-cheng-xue-xi-bi-ji.html", "labels": ["\u8ba1\u7b97\u673a", "\u4ee3\u7801", "\u7f16\u7a0b"], "postTitle": " \u63d0\u793a\u5de5\u7a0b\u5b66\u4e60\u7b14\u8bb0", "postUrl": "post/%20-ti-shi-gong-cheng-xue-xi-bi-ji.html", "postSourceUrl": "https://github.com/hacker4257/hacker4257.github.io/issues/29", "commentNum": 0, "wordCount": 2869, "description": "\r\n\u63d0\u793a\u5de5\u7a0b\uff08Prompt Engineering\uff09\u662f\u4e00\u79cd\u901a\u8fc7\u8bbe\u8ba1\u548c\u4f18\u5316\u7ed9\u5b9a\u7684\u63d0\u793a\uff08Prompt\uff09\u6765\u63a7\u5236AI\u751f\u6210\u5185\u5bb9\u8d28\u91cf\u7684\u6280\u672f\u3002", "top": 0, "createdAt": 1728455471, "style": "", "script": "", "head": "", "ogImage": "https://hacker4257.github.io/ava.jpeg", "createdDate": "2024-10-09", "dateLabelColor": "#bc4c00"}, "P30": {"htmlDir": "docs/post/kai-yuan-da-mo-xing- Llama -shi-zhan.html", "labels": ["\u8ba1\u7b97\u673a", "\u4ee3\u7801", "\u7f16\u7a0b"], "postTitle": "\u5f00\u6e90\u5927\u6a21\u578b Llama \u5b9e\u6218", "postUrl": "post/kai-yuan-da-mo-xing-%20Llama%20-shi-zhan.html", "postSourceUrl": "https://github.com/hacker4257/hacker4257.github.io/issues/30", "commentNum": 0, "wordCount": 3019, "description": "\u8fd1\u5e74\u6765\uff0c\u5f00\u6e90\u5927\u6a21\u578b\u7684\u98de\u901f\u53d1\u5c55\u4e3a\u4eba\u5de5\u667a\u80fd\u5e94\u7528\u9886\u57df\u63d0\u4f9b\u4e86\u66f4\u591a\u7684\u53ef\u80fd\u6027\u3002", "top": 0, "createdAt": 1728528350, "style": "", "script": "", "head": "", "ogImage": "https://hacker4257.github.io/ava.jpeg", "createdDate": "2024-10-10", "dateLabelColor": "#bc4c00"}, "P31": {"htmlDir": "docs/post/ren-gong-zhi-neng-yu-shen-jing-wang-luo-ru-men.html", "labels": ["\u8ba1\u7b97\u673a", "\u4ee3\u7801", "\u7f16\u7a0b"], "postTitle": "\u4eba\u5de5\u667a\u80fd\u4e0e\u795e\u7ecf\u7f51\u7edc\u5165\u95e8", "postUrl": "post/ren-gong-zhi-neng-yu-shen-jing-wang-luo-ru-men.html", "postSourceUrl": "https://github.com/hacker4257/hacker4257.github.io/issues/31", "commentNum": 0, "wordCount": 1791, "description": "# \u4eceRNN\u5230Transformer\u7684\u8fdb\u5316\u4e4b\u8def\r\n\r\n## \u5f15\u8a00\r\n\u60f3\u8c61\u4e00\u4e0b\uff0c\u4f60\u6b63\u5728\u5b66\u4e60\u4e00\u95e8\u65b0\u7684\u8bed\u8a00\u3002", "top": 0, "createdAt": 1728625650, "style": "", "script": "", "head": "", "ogImage": "https://hacker4257.github.io/ava.jpeg", "createdDate": "2024-10-11", "dateLabelColor": "#bc4c00"}}, "singeListJson": {"P5": {"htmlDir": "docs/about.html", "labels": ["about"], "postTitle": "\u81ea\u6211\u4ecb\u7ecd", "postUrl": "about.html", "postSourceUrl": "https://github.com/hacker4257/hacker4257.github.io/issues/5", "commentNum": 0, "wordCount": 822, "description": "hi\uff01\u6211\u662f hacker4257\uff0c\u4e00\u540d\u5168\u6808\u5f00\u53d1\u5de5\u7a0b\u5e08\uff0c\u4e13\u6ce8\u4e8e\u4f7f\u7528 **Golang**\u3001**Python** \u548c **React** \u5f00\u53d1\u9ad8\u6548\u3001\u53ef\u6269\u5c55\u7684\u5e94\u7528\u7a0b\u5e8f\u3002", "top": 0, "createdAt": 1726827716, "style": "", "script": "", "head": "", "ogImage": "https://hacker4257.github.io/ava.jpeg", "createdDate": "2024-09-20", "dateLabelColor": "#bc4c00"}}, "labelColorDict": {"about": "#FBCA04", "\u4e66": "#e4e669", "\u4ee3\u7801": "#008672", "\u597d\u7269": "#cfd3d7", "\u60f3\u6cd5": "#a2eeef", "\u751f\u6d3b": "#0075ca", "\u7535\u5f71": "#77FE31", "\u7b54\u6848": "#4B7368", "\u7f16\u7a0b": "#7057ff", "\u8ba1\u7b97\u673a": "#d73a4a", "\u95ee\u9898": "#d876e3"}, "displayTitle": "Love life Love code", "ogImage": "https://hacker4257.github.io/ava.jpeg", "primerCSS": "<link href='https://mirrors.sustech.edu.cn/cdnjs/ajax/libs/Primer/21.0.7/primer.css' rel='stylesheet' />", "prevUrl": "/index.html", "nextUrl": "disabled"}